PvMail/LICENSE
PvMail/__init__.py
PvMail/cli.py
PvMail/email_model.py
PvMail/ini_config.py
PvMail/ioc_run.sh
PvMail/ioc_screen.sh
PvMail/mailer.py
PvMail/pvMail.ini
PvMail/test.db
PvMail/uic_gui.py
PvMail/utils.py
PvMail/resources/about.ui
PvMail/resources/epicslogo101.gif
PvMail/resources/gui.ui
PvMail/resources/logo-icon.png
PvMail/resources/logo.png
PvMail/resources/logo.vsd
PvMail/resources/logo2-32-32.png
PvMail/resources/logo2.ico
PvMail/resources/logo2.png
PvMail/tests/FIXME-test_mailer.py
PvMail/tests/FIXME-test_pvmail.py
PvMail/tests/__init__.py
PvMail/tests/test_ini_config.py
PvMail-4.0.0.dist-info/METADATA
PvMail-4.0.0.dist-info/WHEEL
PvMail-4.0.0.dist-info/entry_points.txt
PvMail-4.0.0.dist-info/top_level.txt
PvMail-4.0.0.dist-info/RECORD
