Metadata-Version: 2.1
Name: PvMail
Version: 4.0.0
Summary: Watch an EPICS PV. Send email when it changes from 0 to 1.
Author-email: Pete Jemian <jemian@anl.gov>, Kurt Goetze <goetze@anl.gov>
License: Copyright (c) 2009-2024, UChicago Argonne, LLC
Project-URL: Homepage, https://BCDA-APS.github.io/pvmail/
Project-URL: Source, https://github.com/BCDA-APS/pvmail
Project-URL: Bug Tracker, https://github.com/BCDA-APS/pvmail/issues
Keywords: EPICS,PV,email,monitor
Classifier: Development Status :: 5 - Production/Stable
Classifier: Environment :: Console
Classifier: Intended Audience :: Science/Research
Classifier: License :: Freely Distributable
Classifier: License :: Public Domain
Classifier: Programming Language :: Python :: 3.12
Classifier: Programming Language :: Python :: 3.11
Classifier: Programming Language :: Python :: 3.10
Classifier: Programming Language :: Python :: 3.9
Classifier: Programming Language :: Python :: 3.8
Classifier: Programming Language :: Python :: 3
Classifier: Programming Language :: Python
Classifier: Topic :: Scientific/Engineering
Classifier: Topic :: Utilities
Requires-Python: >=3.8
Requires-Dist: pydm
Requires-Dist: pyepics
